p2pstore/__init__.py
p2pstore/client.py
p2pstore/core/__init__.py
p2pstore/core/buffer_registry.py
p2pstore/core/metadata_client.py
p2pstore/core/object_types.py
p2pstore/core/transfer_request.py
p2pstore/core/transport.py
p2pstore/metadata/__init__.py
p2pstore/metadata/redis_client.py
p2pstore/transport/__init__.py
p2pstore/transport/engine_adapter.py
p2pstore/transport/load_balancer.py
p2pstore/transport/rdma_transport.py
p2pstore/transport/tcp_transport.py
p2pstore/transport/transfer_engine.py
p2pstore/utils/__init__.py
p2pstore/utils/common.py
p2pstore/utils/config.py
p2pstore/utils/logger.py
p2pstore/utils/metrics.py
p2pstore/utils/serialization.py
p2pstore/utils/topology.py
p2pstore-0.1.8.post1.dist-info/licenses/LICENSE
p2pstore-0.1.8.post1.dist-info/METADATA
p2pstore-0.1.8.post1.dist-info/WHEEL
p2pstore-0.1.8.post1.dist-info/top_level.txt
p2pstore-0.1.8.post1.dist-info/RECORD
