Metadata-Version: 2.4
Name: p2pstore
Version: 0.1.8.post1
Summary: P2P Store - 基于 RDMA 的高性能分布式数据传输系统, 使用 Redis 作为元数据管理器
Author: Paddle
License-Expression: Apache-2.0
Keywords: p2p,rdma,distributed,tensor,transfer
Classifier: Development Status :: 4 - Beta
Classifier: Intended Audience :: Developers
Classifier: Operating System :: POSIX :: Linux
Classifier: Programming Language :: Python :: 3
Classifier: Programming Language :: Python :: 3.10
Classifier: Programming Language :: Python :: 3.11
Classifier: Programming Language :: Python :: 3.12
Classifier: Topic :: System :: Distributed Computing
Requires-Python: >=3.10
License-File: LICENSE
Requires-Dist: numpy>=1.20.0
Requires-Dist: safetensors>=0.3.0
Requires-Dist: mooncake-transfer-engine==0.3.7
Requires-Dist: redis>=6.4.0
Provides-Extra: paddle
Requires-Dist: paddlepaddle>=2.5.0; extra == "paddle"
Provides-Extra: redis
Requires-Dist: redis>=6.4.0; extra == "redis"
Provides-Extra: dev
Requires-Dist: pytest>=7.0.0; extra == "dev"
Requires-Dist: pytest-asyncio>=0.20.0; extra == "dev"
Requires-Dist: black; extra == "dev"
Requires-Dist: ruff; extra == "dev"
Provides-Extra: benchmark
Requires-Dist: paddlepaddle-gpu>=2.5.0; extra == "benchmark"
Dynamic: license-file
